[
    {
        "customer_id": 1,
        "bought_at": 1613313608,
        "store_id": 735,
        "total": "12121.1",
        "items": [
            {"product_id": 1, "price": 10, "quantity": 10, "name": "natura cos tam xDDDDDDDDDDDDDDDDDDDDDDDDDDDDD"},
            {"product_id": 2, "price": 20, "quantity": 20, "name": "natura cos tam xDDDDDDDDDDDDDDDDDDDDDDDDDDDDD"},
            {"product_id": 3, "price": 30, "quantity": 30, "name": "natura cos tam xDDDDDDDDDDDDDDDDDDDDDDDDDDDDD"},
            {"product_id": 4, "price": 40, "quantity": 40, "name": "natura cos tam xDDDDDDDDDDDDDDDDDDDDDDDDDDDDD"},
            {"product_id": 5, "price": 50, "quantity": 50, "name": "natura cos tam xDDDDDDDDDDDDDDDDDDDDDDDDDDDDD"},
            {"product_id": 6, "price": 60, "quantity": 60, "name": "natura cos tam xDDDDDDDDDDDDDDDDDDDDDDDDDDDDD"},
            {"product_id": 7, "price": 70, "quantity": 70, "name": "natura cos tam xDDDDDDDDDDDDDDDDDDDDDDDDDDDDD"},
            {"product_id": 8, "price": 80, "quantity": 80, "name": "natura cos tam xDDDDDDDDDDDDDDDDDDDDDDDDDDDDD"},
            {"product_id": 9, "price": 90, "quantity": 90, "name": "natura cos tam xDDDDDDDDDDDDDDDDDDDDDDDDDDDDD"},
            {"product_id": 10, "price": 100, "quantity": 100, "name": "natura cos tam xDDDDDDDDDDDDDDDDDDDDDDDDDDDDD"},
            {"product_id": 11, "price": 110, "quantity": 110, "name": "natura cos tam xDDDDDDDDDDDDDDDDDDDDDDDDDDDDD"},
            {"product_id": 12, "price": 120, "quantity": 120, "name": "natura cos tam xDDDDDDDDDDDDDDDDDDDDDDDDDDDDD"},
            {"product_id": 13, "price": 130, "quantity": 130, "name": "natura cos tam xDDDDDDDDDDDDDDDDDDDDDDDDDDDDD"},
            {"product_id": 14, "price": 140, "quantity": 140, "name": "natura cos tam xDDDDDDDDDDDDDDDDDDDDDDDDDDDDD"},
            {"product_id": 15, "price": 150, "quantity": 150, "name": "natura cos tam xDDDDDDDDDDDDDDDDDDDDDDDDDDDDD"},
            {"product_id": 16, "price": 160, "quantity": 160, "name": "natura cos tam xDDDDDDDDDDDDDDDDDDDDDDDDDDDDD"},
            {"product_id": 17, "price": 170, "quantity": 170, "name": "natura cos tam xDDDDDDDDDDDDDDDDDDDDDDDDDDDDD"},
            {"product_id": 18, "price": 180, "quantity": 180, "name": "natura cos tam xDDDDDDDDDDDDDDDDDDDDDDDDDDDDD"},
            {"product_id": 19, "price": 190, "quantity": 190, "name": "natura cos tam xDDDDDDDDDDDDDDDDDDDDDDDDDDDDD"},
            {"product_id": 20, "price": 200, "quantity": 200, "name": "natura cos tam xDDDDDDDDDDDDDDDDDDDDDDDDDDDDD"},
            {"product_id": 21, "price": 210, "quantity": 210, "name": "natura cos tam xDDDDDDDDDDDDDDDDDDDDDDDDDDDDD"},
            {"product_id": 22, "price": 220, "quantity": 220, "name": "natura cos tam xDDDDDDDDDDDDDDDDDDDDDDDDDDDDD"},
            {"product_id": 23, "price": 230, "quantity": 230, "name": "natura cos tam xDDDDDDDDDDDDDDDDDDDDDDDDDDDDD"},
            {"product_id": 24, "price": 240, "quantity": 240, "name": "natura cos tam xDDDDDDDDDDDDDDDDDDDDDDDDDDDDD"},
            {"product_id": 25, "price": 250, "quantity": 250, "name": "natura cos tam xDDDDDDDDDDDDDDDDDDDDDDDDDDDDD"},
            {"product_id": 26, "price": 260, "quantity": 260, "name": "natura cos tam xDDDDDDDDDDDDDDDDDDDDDDDDDDDDD"}
        ]
    },
    {
        "customer_id": 1,
        "bought_at": 1644849608,
        "store_id": 735,
        "total": "2",
        "items": [
            {"product_id": 1, "price": "10", "quantity": 10, "name": "natura cos tam xDDDDDDDDDDDDDDDDDDDDDDDDDDDDD"},
            {"product_id": 2, "price": "20", "quantity": 20, "name": "natura cos tam xDDDDDDDDDDDDDDDDDDDDDDDDDDDDD"},
            {"product_id": 3, "price": "30", "quantity": 30, "name": "natura cos tam xDDDDDDDDDDDDDDDDDDDDDDDDDDDDD"},
            {"product_id": 4, "price": "40", "quantity": 40, "name": "natura cos tam xDDDDDDDDDDDDDDDDDDDDDDDDDDDDD"},
            {"product_id": 5, "price": "50", "quantity": 50, "name": "natura cos tam xDDDDDDDDDDDDDDDDDDDDDDDDDDDDD"},
            {"product_id": 6, "price": "60", "quantity": 60, "name": "natura cos tam xDDDDDDDDDDDDDDDDDDDDDDDDDDDDD"},
            {"product_id": 7, "price": "70", "quantity": 70, "name": "natura cos tam xDDDDDDDDDDDDDDDDDDDDDDDDDDDDD"},
            {"product_id": 8, "price": "80", "quantity": 80, "name": "natura cos tam xDDDDDDDDDDDDDDDDDDDDDDDDDDDDD"},
            {"product_id": 9, "price": "90", "quantity": 90, "name": "natura cos tam xDDDDDDDDDDDDDDDDDDDDDDDDDDDDD"},
            {"product_id": 10, "price": "100", "quantity": 100, "name": "natura cos tam xDDDDDDDDDDDDDDDDDDDDDDDDDDDDD"},
            {"product_id": 11, "price": "110", "quantity": 110, "name": "natura cos tam xDDDDDDDDDDDDDDDDDDDDDDDDDDDDD"},
            {"product_id": 12, "price": "120", "quantity": 120, "name": "natura cos tam xDDDDDDDDDDDDDDDDDDDDDDDDDDDDD"},
            {"product_id": 13, "price": "130", "quantity": 130, "name": "natura cos tam xDDDDDDDDDDDDDDDDDDDDDDDDDDDDD"},
            {"product_id": 14, "price": "140", "quantity": 140, "name": "natura cos tam xDDDDDDDDDDDDDDDDDDDDDDDDDDDDD"},
            {"product_id": 15, "price": "150", "quantity": 150, "name": "natura cos tam xDDDDDDDDDDDDDDDDDDDDDDDDDDDDD"},
            {"product_id": 16, "price": "160", "quantity": 160, "name": "natura cos tam xDDDDDDDDDDDDDDDDDDDDDDDDDDDDD"},
            {"product_id": 17, "price": "170", "quantity": 170, "name": "natura cos tam xDDDDDDDDDDDDDDDDDDDDDDDDDDDDD"},
            {"product_id": 18, "price": "180", "quantity": 180, "name": "natura cos tam xDDDDDDDDDDDDDDDDDDDDDDDDDDDDD"},
            {"product_id": 19, "price": "190", "quantity": 190, "name": "natura cos tam xDDDDDDDDDDDDDDDDDDDDDDDDDDDDD"},
            {"product_id": 20, "price": "200", "quantity": 200, "name": "natura cos tam xDDDDDDDDDDDDDDDDDDDDDDDDDDDDD"},
            {"product_id": 21, "price": "210", "quantity": 210, "name": "natura cos tam xDDDDDDDDDDDDDDDDDDDDDDDDDDDDD"},
            {"product_id": 22, "price": "220", "quantity": 220, "name": "natura cos tam xDDDDDDDDDDDDDDDDDDDDDDDDDDDDD"},
            {"product_id": 23, "price": "230", "quantity": 230, "name": "natura cos tam xDDDDDDDDDDDDDDDDDDDDDDDDDDDDD"},
            {"product_id": 24, "price": "240", "quantity": 240, "name": "natura cos tam xDDDDDDDDDDDDDDDDDDDDDDDDDDDDD"}
        ]
    },
    {
        "customer_id": 2,
        "bought_at": 1581691208,
        "store_id": 735,
        "total": "12121.1",
        "items": [
            {"product_id": 1, "price": "10", "quantity": 10, "name": "natura cos tam xDDDDDDDDDDDDDDDDDDDDDDDDDDDDD"},
            {"product_id": 2, "price": "20", "quantity": 20, "name": "natura cos tam xDDDDDDDDDDDDDDDDDDDDDDDDDDDDD"},
            {"product_id": 3, "price": "30", "quantity": 30, "name": "natura cos tam xDDDDDDDDDDDDDDDDDDDDDDDDDDDDD"},
            {"product_id": 4, "price": "40", "quantity": 40, "name": "natura cos tam xDDDDDDDDDDDDDDDDDDDDDDDDDDDDD"},
            {"product_id": 5, "price": "50", "quantity": 50, "name": "natura cos tam xDDDDDDDDDDDDDDDDDDDDDDDDDDDDD"},
            {"product_id": 6, "price": "60", "quantity": 60, "name": "natura cos tam xDDDDDDDDDDDDDDDDDDDDDDDDDDDDD"},
            {"product_id": 7, "price": "70", "quantity": 70, "name": "natura cos tam xDDDDDDDDDDDDDDDDDDDDDDDDDDDDD"},
            {"product_id": 8, "price": "80", "quantity": 80, "name": "natura cos tam xDDDDDDDDDDDDDDDDDDDDDDDDDDDDD"},
            {"product_id": 9, "price": "90", "quantity": 90, "name": "natura cos tam xDDDDDDDDDDDDDDDDDDDDDDDDDDDDD"},
            {"product_id": 10, "price": "100", "quantity": 100, "name": "natura cos tam xDDDDDDDDDDDDDDDDDDDDDDDDDDDDD"},
            {"product_id": 11, "price": "110", "quantity": 110, "name": "natura cos tam xDDDDDDDDDDDDDDDDDDDDDDDDDDDDD"},
            {"product_id": 12, "price": "120", "quantity": 120, "name": "natura cos tam xDDDDDDDDDDDDDDDDDDDDDDDDDDDDD"},
            {"product_id": 13, "price": "130", "quantity": 130, "name": "natura cos tam xDDDDDDDDDDDDDDDDDDDDDDDDDDDDD"},
            {"product_id": 14, "price": "140", "quantity": 140, "name": "natura cos tam xDDDDDDDDDDDDDDDDDDDDDDDDDDDDD"},
            {"product_id": 15, "price": "150", "quantity": 150, "name": "natura cos tam xDDDDDDDDDDDDDDDDDDDDDDDDDDDDD"},
            {"product_id": 16, "price": "160", "quantity": 160, "name": "natura cos tam xDDDDDDDDDDDDDDDDDDDDDDDDDDDDD"},
            {"product_id": 17, "price": "170", "quantity": 170, "name": "natura cos tam xDDDDDDDDDDDDDDDDDDDDDDDDDDDDD"},
            {"product_id": 18, "price": "180", "quantity": 180, "name": "natura cos tam xDDDDDDDDDDDDDDDDDDDDDDDDDDDDD"},
            {"product_id": 19, "price": "190", "quantity": 190, "name": "natura cos tam xDDDDDDDDDDDDDDDDDDDDDDDDDDDDD"},
            {"product_id": 20, "price": "200", "quantity": 200, "name": "natura cos tam xDDDDDDDDDDDDDDDDDDDDDDDDDDDDD"},
            {"product_id": 21, "price": "210", "quantity": 210, "name": "natura cos tam xDDDDDDDDDDDDDDDDDDDDDDDDDDDDD"},
            {"product_id": 22, "price": "220", "quantity": 220, "name": "natura cos tam xDDDDDDDDDDDDDDDDDDDDDDDDDDDDD"},
            {"product_id": 23, "price": "230", "quantity": 230, "name": "natura cos tam xDDDDDDDDDDDDDDDDDDDDDDDDDDDDD"},
            {"product_id": 24, "price": "240", "quantity": 240, "name": "natura cos tam xDDDDDDDDDDDDDDDDDDDDDDDDDDDDD"}
        ]
    }
]